docs/conf.py
examples/fluid_mech.py
examples/tr_curve.py
mudu/__init__.py
mudu/base.py
mudu/dimensions.py
mudu/exceptions.py
mudu/units.py
mudu-1.1.501.dist-info/METADATA
mudu-1.1.501.dist-info/WHEEL
mudu-1.1.501.dist-info/top_level.txt
mudu-1.1.501.dist-info/RECORD
