Metadata-Version: 2.4
Name: mudu
Version: 1.1.501
Summary: A python package for unit-aware numerical data handling.
Author-email: Kolawole Andrew <andrewolakola@gmail.com>
License: MIT
Project-URL: Homepage, https://github.com/techkaduna/mudu
Project-URL: Repository, https://github.com/techkaduna/mudu
Keywords: units,physics,engineering,dimension-analysis,unit-conversion,unit-aware computing
Classifier: Development Status :: 4 - Beta
Classifier: Intended Audience :: Science/Research
Classifier: Intended Audience :: Developers
Classifier: Intended Audience :: Education
Classifier: License :: OSI Approved :: MIT License
Classifier: Programming Language :: Python :: 3
Classifier: Topic :: Scientific/Engineering
Classifier: Topic :: Scientific/Engineering :: Physics
Classifier: Operating System :: OS Independent
Requires-Python: >=3.12
Requires-Dist: sympy>=1.13.3
